.gitignore
.gitlab-ci.yml
.pre-commit-config.yaml
.profile
.travis.yml
AUTHORS.rst
CHANGELOG.md
LICENSE.txt
MANIFEST.in
README.rst
codecov.yml
example-requirements.txt
justfile
requirements.txt
setup.cfg
setup.py
test-requirements.txt
README.md_files/autocomplete.webm
data_files/5.cs.fau.conrad.desktop
data_files/5.cs.fau.conrad_compare.desktop
data_files/5.cs.fau.conrad_imagej.desktop
docs/Makefile
docs/authors.rst
docs/changes.rst
docs/conf.py
docs/index.rst
docs/license.rst
docs/_static/.gitignore
pyconrad/__init__.py
pyconrad/__main__.py
pyconrad/_cache.py
pyconrad/_classgetter.py
pyconrad/_deprecated.py
pyconrad/_download_conrad.py
pyconrad/_extend_conrad_classes.py
pyconrad/_imageutils.py
pyconrad/_java_pyconrad.py
pyconrad/_pyconrad.py
pyconrad/_pyconrad_run.py
pyconrad/_pygrid.py
pyconrad/_scripts.py
pyconrad/_vtk.py
pyconrad/_windowlistener.py
pyconrad/autoinit.py
pyconrad/config.py
pyconrad/constants.py
pyconrad/dicom_utils.py
pyconrad/opencl.py
pyconrad/phantoms.py
pyconrad.egg-info/PKG-INFO
pyconrad.egg-info/SOURCES.txt
pyconrad.egg-info/dependency_links.txt
pyconrad.egg-info/entry_points.txt
pyconrad.egg-info/requires.txt
pyconrad.egg-info/top_level.txt
pyconrad_examples/opencl.py
pyconrad_examples/opencl_custom_kernel.py
pyconrad_examples/first_steps/_0_start_conrad.py
pyconrad_examples/first_steps/_1_basic_example.py
pyconrad_examples/first_steps/_2_start_reconstruction_filter_pipeline.py
pyconrad_examples/first_steps/_3_numpy_and_conrad.py
pyconrad_examples/first_steps/_4_what_does_not_work_as_expected.py
pyconrad_examples/first_steps/_5_run_ij_commands.py
pyconrad_examples/java/SampleClass.java
pyconrad_examples/java/use_own_java_class.py
pyconrad_examples/plotting/create_tikz_plot.py
pyconrad_examples/plotting/visualize_conradgrid_in_python.py
pyconrad_examples/reconstruction/basic_reco_example.py
pyconrad_examples/reconstruction/sart_cl.py
pyconrad_examples/visualization/imshow.py
tests/small_domain.vti
tests/test_classgetter.py
tests/test_config.py
tests/test_conrad_class_extension.py
tests/test_examples.py
tests/test_gui.py
tests/test_imshow.py
tests/test_installation.py
tests/test_java_import.py
tests/test_opencl.py
