Metadata-Version: 2.1
Name: pyconrad
Version: 0.7.7
Summary: Python wrapper for CONRAD (https://www5.cs.fau.de/conrad/), a framework for cone beam radiography
Home-page: https://git5.cs.fau.de/PyConrad/pyCONRAD/
Author: Andreas Maier
Author-email: andreas.maier@fau.de
License: GPL 3.0
Platform: UNKNOWN
Classifier: Development Status :: 4 - Beta
Classifier: Programming Language :: Python
Provides-Extra: opencl
Provides-Extra: vtk
